doc/source/conf.py
ldap_faker/__init__.py
ldap_faker/db.py
ldap_faker/faker.py
ldap_faker/hooks.py
ldap_faker/logging.py
ldap_faker/py.typed
ldap_faker/types.py
ldap_faker/unittest.py
ldap_faker/servers/__init__.py
ldap_faker/servers/server_389.py
ldap_faker/test/__init__.py
ldap_faker/test/app.py
ldap_faker/test/app2.py
ldap_faker/test/test_FakeLDAPObject.py
ldap_faker/test/test_LDAPServerFactory.py
ldap_faker/test/test_ObjectStore.py
ldap_faker/test/test_server_389.py
ldap_faker/test/test_unittest.py
ldap_faker/test/test_vlv.py
ldap_faker/test/test_vlv_rfc_compliance.py
python_ldap_faker-1.3.4.dist-info/licenses/LICENSE.txt
typings/ldap/__init__.pyi
typings/ldap/async.pyi
typings/ldap/asyncsearch.pyi
typings/ldap/cidict.pyi
typings/ldap/compat.pyi
typings/ldap/constants.pyi
typings/ldap/dn.pyi
typings/ldap/filter.pyi
typings/ldap/functions.pyi
typings/ldap/ldapobject.pyi
typings/ldap/logger.pyi
typings/ldap/modlist.pyi
typings/ldap/pkginfo.pyi
typings/ldap/resiter.pyi
typings/ldap/sasl.pyi
typings/ldap/syncrepl.pyi
typings/ldap/controls/__init__.pyi
typings/ldap/controls/libldap.pyi
typings/ldap/controls/simple.pyi
typings/ldap/extop/__init__.pyi
typings/ldap/extop/dds.pyi
typings/ldap/extop/passwd.pyi
typings/ldap/schema/__init__.pyi
typings/ldap/schema/models.pyi
typings/ldap/schema/subentry.pyi
typings/ldap/schema/tokenizer.pyi
typings/ldap_filter/__init__.pyi
typings/ldap_filter/filter.pyi
typings/ldap_filter/parser.pyi
typings/ldap_filter/soundex.pyi
python_ldap_faker-1.3.4.dist-info/METADATA
python_ldap_faker-1.3.4.dist-info/WHEEL
python_ldap_faker-1.3.4.dist-info/top_level.txt
python_ldap_faker-1.3.4.dist-info/RECORD
