Metadata-Version: 2.4
Name: python-ldap-faker
Version: 1.3.4
Summary: Fake python-ldap functions, objects and methods for use in testing.
Author-email: Caltech IMSS ADS <cmalek@caltech.edu>
Project-URL: Homepage, https://github.com/caltechads/python-ldap-faker
Project-URL: Documentation, https://python-ldap-faker.readthedocs.io/en/latest/
Project-URL: Source, https://github.com/caltechads/python-ldap-faker
Project-URL: Issues, https://github.com/caltechads/python-ldap-faker/issues
Keywords: ldap,testing
Classifier: Development Status :: 4 - Beta
Classifier: Environment :: Console
Classifier: Intended Audience :: Developers
Classifier: License :: OSI Approved :: BSD License
Classifier: Operating System :: OS Independent
Classifier: Programming Language :: Python
Classifier: Programming Language :: Python :: 3
Classifier: Programming Language :: Python :: 3.10
Classifier: Programming Language :: Python :: 3.11
Classifier: Programming Language :: Python :: 3.12
Classifier: Programming Language :: Python :: 3.13
Classifier: Topic :: Software Development :: Testing
Classifier: Typing :: Typed
Requires-Python: >=3.10
License-File: LICENSE.txt
Requires-Dist: python-ldap>=3.4.4
Requires-Dist: case-insensitive-dictionary>=0.2.1
Requires-Dist: ldap-filter>=0.2.0
Requires-Dist: asn1>=3.1.0
Dynamic: license-file
